compileMD/__init__.py
compileMD/compile_markdown.py
compileMD-0.2.1.dist-info/METADATA
compileMD-0.2.1.dist-info/WHEEL
compileMD-0.2.1.dist-info/entry_points.txt
compileMD-0.2.1.dist-info/top_level.txt
compileMD-0.2.1.dist-info/RECORD
